src/nebari_plugin_cert_manager_chart/__about__.py
src/nebari_plugin_cert_manager_chart/__init__.py
src/nebari_plugin_cert_manager_chart/plugin.py
src/nebari_plugin_cert_manager_chart/template/main.tf
src/nebari_plugin_cert_manager_chart/template/outputs.tf
src/nebari_plugin_cert_manager_chart/template/variables.tf
src/nebari_plugin_cert_manager_chart/template/versions.tf
src/nebari_plugin_cert_manager_chart/template/chart/Chart.yaml
src/nebari_plugin_cert_manager_chart/template/chart/values.yaml
src/nebari_plugin_cert_manager_chart/template/chart/templates/certificates.yaml
src/nebari_plugin_cert_manager_chart/template/chart/templates/issuers.yaml
nebari_plugin_cert_manager_chart-0.0.1.dist-info/METADATA
nebari_plugin_cert_manager_chart-0.0.1.dist-info/WHEEL
nebari_plugin_cert_manager_chart-0.0.1.dist-info/entry_points.txt
nebari_plugin_cert_manager_chart-0.0.1.dist-info/licenses/LICENSE
nebari_plugin_cert_manager_chart-0.0.1.dist-info/RECORD
